{
    "colors": {
        "activityBar.background": "#2b2d30",
        "activityBar.border": "#2b2d30",
        "banner.background": "#2b2d30",
        "breadcrumb.background": "#2b2d30",
        "editor.background": "#1e1f22",
        "editor.lineHighlightBackground": "#26282E",
        "editorBracketPairGuide.activeBackground1": "#56585a",
        "editorBracketPairGuide.activeBackground2": "#56585a",
        "editorBracketPairGuide.activeBackground3": "#56585a",
        "editorBracketPairGuide.activeBackground4": "#56585a",
        "editorBracketPairGuide.activeBackground5": "#56585a",
        "editorBracketPairGuide.activeBackground6": "#56585a",
        "editorBracketPairGuide.background1": "#2b2d30",
        "editorBracketPairGuide.background2": "#2b2d30",
        "editorBracketPairGuide.background3": "#2b2d30",
        "editorBracketPairGuide.background4": "#2b2d30",
        "editorBracketPairGuide.background5": "#2b2d30",
        "editorBracketPairGuide.background6": "#2b2d30",
        "editorCursor.foreground": "#CED0D6",
        "editorGroup.emptyBackground": "#2b2d30",
        "editorGroupHeader.tabsBackground": "#1e1f22",
        "editorGutter.background": "#1e1f22",
        "editorHoverWidget.background": "#2b2d30",
        "editorIndentGuide.activeBackground": "#666870",
        "editorIndentGuide.background": "#313438",
        "editorLineNumber.foreground": "#4B5059",
        "editorRuler.foreground": "#393B40",
        "editorSuggestWidget.background": "#2b2d30",
        "editorSuggestWidget.selectedBackground": "#3b3b39",
        "editorWhitespace.foreground": "#6F737A",
        "editorWidget.background": "#2b2d30",
        "input.background": "#1d1d1d",
        "menu.background": "#2b2d30",
        "notebook.cellBorderColor": "#2b2d30",
        "notebook.cellEditorBackground": "#2b2d30",
        "panel.background": "#2b2d30",
        "scrollbar.shadow": "#131313",
        "scrollbarSlider.background": "#474747a8",
        "sideBar.background": "#2b2d30",
        "sideBar.border": "#1e1f22",
        "sideBarSectionHeader.background": "#2b2d30",
        "sideBarSectionHeader.border": "#2b2d30",
        "statusBar.background": "#2b2d30",
        "statusBar.border": "#1e1f22",
        "statusBar.noFolderBackground": "#2b2d30",
        "statusBarItem.remoteBackground": "#005a95",
        "tab.activeBackground": "#1e1f22",
        "tab.activeBorder": "#005a95",
        "tab.inactiveBackground": "#1e1f22",
        "terminal.ansiBlack": "#151515",
        "terminal.ansiBlue": "#6C99BB",
        "terminal.ansiBrightBlack": "#505050",
        "terminal.ansiBrightBlue": "#6C99BB",
        "terminal.ansiBrightCyan": "#7DD6CF",
        "terminal.ansiBrightGreen": "#7E8E50",
        "terminal.ansiBrightMagenta": "#9F4E85",
        "terminal.ansiBrightRed": "#AC4142",
        "terminal.ansiBrightWhite": "#F5F5F5",
        "terminal.ansiBrightYellow": "#E5B567",
        "terminal.ansiCyan": "#7DD6CF",
        "terminal.ansiGreen": "#7E8E50",
        "terminal.ansiMagenta": "#9F4E85",
        "terminal.ansiRed": "#AC4142",
        "terminal.ansiWhite": "#D0D0D0",
        "terminal.ansiYellow": "#E5B567",
        "terminal.background": "#1e1f22",
        "terminal.border": "#1e1f22",
        "terminal.foreground": "#bcbec4",
        "terminal.selectionBackground": "#303030",
        "terminalCursor.foreground": "#D0D0D0",
        "titleBar.activeBackground": "#2b2d30",
        "titleBar.inactiveBackground": "#2b2d30",
        "welcomePage.background": "#2b2d30"
    },
    "name": "JetBrains Dark Theme",
    "tokenColors": [
        {
            "scope": [
                "comment",
                "comment.block.go",
                "comment.line.double-slash.go",
                "comment.line.double-slash.groovy",
                "comment.line.double-slash.jenkinsfile",
                "comment.line.number-sign.shell",
                "entity.name.type.lifetime.rust",
                "punctuation.definition.comment.go",
                "punctuation.definition.lifetime.rust"
            ],
            "settings": {
                "foreground": "#7a7e85"
            }
        },
        {
            "scope": [
                "constant.language.java",
                "storage.modifier.import.java",
                "storage.modifier.package.java",
                "constant.other.key.java",
                "entity.name.type",
                "entity.name.type.alias.tsx",
                "entity.name.type.class.java",
                "entity.name.type.class.python",
                "entity.name.type.declaration.rust",
                "entity.name.type.enum.java",
                "entity.name.type.enum.rust",
                "entity.name.type.interface.tsx",
                "entity.name.type.module.tsx",
                "entity.name.type.rust",
                "entity.name.type.struct.rust",
                "entity.name.type.trait.rust",
                "entity.name.type.ts",
                "entity.name.type.tsx",
                "entity.other.attribute-name.html",
                "entity.other.attribute-name.tsx",
                "keyword.control.ternary.java",
                "keyword.operator.access.dot.rust",
                "keyword.operator.address.go",
                "keyword.operator.arithmetic.go",
                "keyword.operator.arithmetic.java",
                "keyword.operator.arithmetic.python",
                "keyword.operator.arrow.fat.rust",
                "keyword.operator.arrow.skinny.rust",
                "keyword.operator.assignment.equal.rust",
                "keyword.operator.assignment.go",
                "keyword.operator.assignment.java",
                "keyword.operator.assignment.js",
                "keyword.operator.assignment.python",
                "keyword.operator.assignment.rust",
                "keyword.operator.assignment.ts",
                "keyword.operator.assignment.tsx",
                "keyword.operator.borrow.and.rust",
                "keyword.operator.comparison.go",
                "keyword.operator.comparison.java",
                "keyword.operator.comparison.python",
                "keyword.operator.comparison.rust",
                "keyword.operator.comparison.ts",
                "keyword.operator.decrement.go",
                "keyword.operator.dereference.rust",
                "keyword.operator.go",
                "keyword.operator.increment-decrement.java",
                "keyword.operator.increment.go",
                "keyword.operator.key-value.rust",
                "keyword.operator.logical.go",
                "keyword.operator.logical.java",
                "keyword.operator.logical.ts",
                "keyword.operator.logical.tsx",
                "keyword.operator.math.rust",
                "keyword.operator.namespace.rust",
                "keyword.operator.optional.ts",
                "keyword.operator.relational.ts",
                "keyword.operator.spread.js",
                "keyword.operator.spread.tsx",
                "keyword.operator.ternary.ts",
                "keyword.operator.ternary.tsx",
                "keyword.operator.type.annotation.ts",
                "keyword.operator.type.annotation.tsx",
                "keyword.operator.unpacking.arguments.python",
                "keyword.other.unit.percentage.css",
                "meta.function-call.generic.python",
                "meta.jsx.children.tsx",
                "meta.property-name.css",
                "punctuation.definition.block.sequence.item.yaml",
                "punctuation.definition.block.tsx",
                "punctuation.definition.entity.css",
                "punctuation.definition.table.toml",
                "punctuation.section.block.begin.bracket.curly.java",
                "punctuation.section.block.end.bracket.curly.java",
                "punctuation.section.embedded.begin.tsx",
                "punctuation.section.embedded.end.tsx",
                "punctuation.section.function.begin.bracket.round.css",
                "punctuation.section.function.end.bracket.round.css",
                "punctuation.section.property-list.begin.bracket.curly.css",
                "punctuation.section.property-list.end.bracket.curly.css",
                "punctuation.separator.comma.tsx",
                "punctuation.separator.delimiter.java",
                "punctuation.separator.key-value.css",
                "punctuation.separator.key-value.js",
                "punctuation.separator.key-value.mapping.yaml",
                "punctuation.separator.key-value.tsx",
                "punctuation.separator.list.comma.css",
                "punctuation.terminator.rule.css",
                "storage.type.function.arrow.java",
                "storage.type.function.arrow.ts",
                "storage.type.function.arrow.tsx",
                "storage.type.generic.java",
                "storage.type.generic.wildcard.java",
                "storage.type.java",
                "storage.type.object.array.java",
                "string.unquoted.plain.out.yaml",
                "variable.language.java",
                "variable.language.wildcard.java",
                "variable.other",
                "variable.other.object.js",
                "variable.other.object.ts"
            ],
            "settings": {
                "foreground": "#bcbec4"
            }
        },
        {
            "scope": [
                "constant.numeric",
                "variable.language"
            ],
            "settings": {
                "foreground": "#2aacb8"
            }
        },
        {
            "scope": [
                "constant.character.escape.backslash.rust",
                "constant.character.escape.bit.rust",
                "constant.character.escape.rust",
                "constant.character.escape.unicode.rust",
                "constant.character.format.placeholder.other.python",
                "constant.language.boolean.false.js",
                "constant.language.boolean.go",
                "constant.language.boolean.true.js",
                "constant.language.go",
                "entity.name.tag.css",
                "entity.name.tag.yaml",
                "entity.other.attribute-name.id.css",
                "keyword",
                "keyword.control.go",
                "keyword.control.groovy",
                "keyword.control.jenkinsfile",
                "keyword.control.rust",
                "keyword.control.shell",
                "keyword.operator",
                "keyword.operator.logical.python",
                "meta.interpolation.rust",
                "punctuation.definition.interpolation.rust",
                "punctuation.definition.template-expression.begin.ts",
                "punctuation.definition.template-expression.end.ts",
                "source.yaml",
                "storage.modifier",
                "storage.modifier.async.ts",
                "storage.modifier.async.tsx",
                "storage.modifier.extends.java",
                "storage.modifier.implements.java",
                "storage.modifier.java",
                "storage.modifier.mut.rust",
                "storage.modifier.rust",
                "storage.modifier.sql",
                "storage.type",
                "storage.type.class.python",
                "storage.type.function.async.python",
                "storage.type.function.python",
                "storage.type.function.ts",
                "storage.type.function.tsx",
                "storage.type.groovy",
                "storage.type.interface.tsx",
                "storage.type.jenkinsfile",
                "storage.type.module.rust",
                "storage.type.primitive.array.java",
                "storage.type.primitive.java",
                "storage.type.rust",
                "storage.type.ts",
                "storage.type.tsx",
                "storage.type.type.tsx",
                "support.type.primitive.tsx",
                "support.type.property-name.json",
                "support.type.property-name.json punctuation",
                "support.type.property-name.table.toml",
                "support.type.property-name.toml",
                "variable.language.rust",
                "variable.language.self.rust",
                "variable.language.special.self.python",
                "variable.language.this.java"
            ],
            "settings": {
                "foreground": "#cf8e6d"
            }
        },
        {
            "scope": [
                "entity.name.type.groovy",
                "entity.name.type.jenkinsfile",
                "meta.at-rule.media.header.css",
                "meta.declaration.annotation.java",
                "meta.tag.attributes.tsx",
                "storage.type.sql",
                "support.function.builtin.python",
                "support.type.exception.python",
                "support.type.python"
            ],
            "settings": {
                "foreground": "#8888c6"
            }
        },
        {
            "scope": [
                "keyword.other.unit.ms.css",
                "keyword.other.unit.px.css",
                "keyword.other.unit.rem.css",
                "keyword.other.unit.vh.css",
                "keyword.other.unit.vw.css",
                "meta.property-list.css",
                "meta.property-value.css",
                "punctuation.definition.string",
                "punctuation.separator.key-value.html",
                "storage.type.string.python",
                "string",
                "string.quoted.double.go",
                "string.quoted.double.groovy",
                "string.quoted.double.jenkinsfile",
                "string.quoted.double.shell",
                "string.quoted.raw.go",
                "string.quoted.single.groovy",
                "string.quoted.single.jenkinsfile",
                "string.quoted.single.shell"
            ],
            "settings": {
                "foreground": "#6aab73"
            }
        },
        {
            "scope": "variable.parameter.function-call.python",
            "settings": {
                "foreground": "#a94927"
            }
        },
        {
            "scope": "string.quoted.docstring.multi.python",
            "settings": {
                "foreground": "#5d7e68"
            }
        },
        {
            "scope": [
                "entity.name.function.decorator.python",
                "meta.attribute.rust",
                "punctuation.definition.annotation-arguments.begin.bracket.round.java",
                "punctuation.definition.annotation-arguments.end.bracket.round.java",
                "punctuation.definition.annotation.java",
                "storage.type.annotation.java"
            ],
            "settings": {
                "foreground": "#b3ae60"
            }
        },
        {
            "scope": [
                "entity.name.tag.html",
                "entity.name.tag.localname.xml",
                "entity.name.tag.tsx",
                "entity.other.attribute-name.class.css",
                "entity.other.attribute-name.pseudo-class.css",
                "punctuation.definition.tag.begin.html",
                "punctuation.definition.tag.begin.tsx",
                "punctuation.definition.tag.end.html",
                "punctuation.definition.tag.end.tsx",
                "punctuation.definition.tag.xml",
                "support.function.misc.css",
                "support.function.url.css"
            ],
            "settings": {
                "foreground": "#d5b778"
            }
        },
        {
            "scope": [
                "entity.name.function.macro.rules.rust",
                "keyword.operator.macro.dollar.rust",
                "variable.other.metavariable.specifier.rust"
            ],
            "settings": {
                "foreground": "#ffc66d"
            }
        },
        {
            "scope": [
                "meta.object-literal.key.js",
                "meta.object-literal.key.tsx",
                "variable.other.constant",
                "variable.other.constant.go",
                "variable.other.definition.java",
                "variable.other.object.property.java",
                "variable.other.property.js",
                "variable.other.property.ts",
                "variable.other.property.tsx"
            ],
            "settings": {
                "foreground": "#c77dbb"
            }
        },
        {
            "scope": [
                "entity.name.function.go",
                "entity.name.function.groovy",
                "entity.name.function.jenkinsfile",
                "entity.name.function.js",
                "entity.name.function.python",
                "entity.name.function.shell",
                "entity.name.function.ts",
                "entity.name.function.tsx",
                "support.function.builtin.go",
                "support.function.builtin.shell"
            ],
            "settings": {
                "foreground": "#56a8f5"
            }
        },
        {
            "scope": [
                "entity.name.type.parameter"
            ],
            "settings": {
                "foreground": "#16baac"
            }
        },
        {
            "scope": [
                "comment.block.documentation",
                "comment.block.documentation.go"
            ],
            "settings": {
                "foreground": "#5f826b"
            }
        },
        {
            "scope": [
                "support.class.component.tsx"
            ],
            "settings": {
                "foreground": "#2fbaa3"
            }
        },
        {
            "settings": {
                "activeGuide": "#CACED6",
                "background": "#1e1f22",
                "caret": "#528BFF",
                "findHighlight": "#FFE792",
                "foreground": "#ABB2BF",
                "guide": "#3C4049",
                "invisibles": "#3C4049",
                "lineHighlight": "#2C313A",
                "selection": "#3E4451"
            }
        }
    ],
    "type": "dark"
}